Metadata-Version: 2.4
Name: esprima2
Version: 5.0.0
Summary: high-performance javascript parser, tokenizer and lexical analyser
Home-page: https://github.com/s0md3v/esprima2
Author: Somdev Sangwan (s0md3v)
Author-email: s0md3v@gmail.com
License: BSD-2-Clause
Keywords: esprima,ecmascript,javascript,parser,ast
Classifier: Development Status :: 5 - Production/Stable
Classifier: Intended Audience :: Developers
Classifier: License :: OSI Approved :: BSD License
Classifier: Operating System :: OS Independent
Classifier: Topic :: Software Development :: Code Generators
Classifier: Topic :: Software Development :: Compilers
Classifier: Topic :: Software Development :: Libraries :: Python Modules
Classifier: Topic :: Text Processing :: General
Classifier: Programming Language :: Python
Classifier: Programming Language :: Python :: 3
Classifier: Programming Language :: Python :: 3.3
Classifier: Programming Language :: Python :: 3.4
Classifier: Programming Language :: Python :: 3.5
Classifier: Programming Language :: Python :: 3.6
License-File: LICENSE.BSD
Dynamic: license-file
